{
 "security_code": "000425",
 "retrieved_at_utc": "2026-07-10T13:36:46+00:00",
 "quote": {
  "price": 8.43,
  "change_pct": 0.96,
  "pe_dynamic": 12.0,
  "pe_ttm": 14.98,
  "pb": 1.64,
  "total_market_cap": 98725504085,
  "float_market_cap": 75874681668,
  "quote_time": 1783668849,
  "name": "徐工机械",
  "source_url": "https://push2.eastmoney.com/api/qt/ulist.np/get?fltt=2&invt=2&fields=f2%2Cf3%2Cf9%2Cf12%2Cf14%2Cf20%2Cf21%2Cf23%2Cf115%2Cf124&secids=0.300415%2C0.300435%2C1.688516%2C1.603556%2C0.002906%2C0.300470%2C0.300014%2C0.300073%2C0.000425"
 },
 "source_urls": {
  "finance": "https://datacenter.eastmoney.com/securities/api/data/get?filter=%28SECUCODE%3D%22000425.SZ%22%29&client=APP&source=HSF10&type=RPT_F10_FINANCE_MAINFINADATA&sty=APP_F10_MAINFINADATA&st=REPORT_DATE&ps=40&sr=-1",
  "valuation_history": "https://datacenter-web.eastmoney.com/api/data/v1/get?reportName=RPT_VALUEANALYSIS_DET&columns=ALL&filter=%28SECURITY_CODE%3D%22000425%22%29&pageNumber=1&pageSize=1250&sortTypes=-1&sortColumns=TRADE_DATE&source=WEB&client=WEB",
  "performance_predict": "https://datacenter-web.eastmoney.com/api/data/v1/get?reportName=RPT_PUBLIC_OP_NEWPREDICT&columns=ALL&filter=%28SECURITY_CODE%3D%22000425%22%29&pageNumber=1&pageSize=6&sortTypes=-1&sortColumns=NOTICE_DATE&source=WEB&client=WEB",
  "performance_express": "https://datacenter-web.eastmoney.com/api/data/v1/get?reportName=RPT_FCI_PERFORMANCEE&columns=ALL&filter=%28SECURITY_CODE%3D%22000425%22%29&pageNumber=1&pageSize=4&sortTypes=-1&sortColumns=REPORT_DATE&source=WEB&client=WEB",
  "profit_forecast": "https://emweb.securities.eastmoney.com/PC_HSF10/ProfitForecast/PageAjax?code=SZ000425"
 },
 "fetch_status": "fetched",
 "fetch_error": "",
 "finance_periods": [
  {
   "REPORT_DATE": "2026-03-31 00:00:00",
   "REPORT_TYPE": "一季报",
   "REPORT_DATE_NAME": "2026一季报",
   "NOTICE_DATE": "2026-04-29 00:00:00",
   "UPDATE_DATE": "2026-04-29 00:00:00",
   "TOTALOPERATEREVE": 29790570752.92,
   "TOTALOPERATEREVETZ": 9.258451752041,
   "PARENTNETPROFIT": 2056440952.77,
   "PARENTNETPROFITTZ": 0.862371216565,
   "KCFJCXSYJLR": 2023512920.97,
   "KCFJCXSYJLRTZ": 0.804352090167,
   "EPSJB": 0.175,
   "XSMLL": 22.0515134966,
   "XSJLL": 7.0043271303,
   "ROEJQ": 3.34,
   "ROIC": 2.107293296576,
   "MGJYXJJE": 0.183166534756,
   "JYXJLYYSR": 0.072236052586,
   "ZCFZL": 65.0409829775
  },
  {
   "REPORT_DATE": "2025-12-31 00:00:00",
   "REPORT_TYPE": "年报",
   "REPORT_DATE_NAME": "2025年报",
   "NOTICE_DATE": "2026-04-29 00:00:00",
   "UPDATE_DATE": "2026-04-29 00:00:00",
   "TOTALOPERATEREVE": 100822903512.12,
   "TOTALOPERATEREVETZ": 8.368128114659,
   "PARENTNETPROFIT": 6572221644.27,
   "PARENTNETPROFITTZ": 8.959353407059,
   "KCFJCXSYJLR": 6550268856.67,
   "KCFJCXSYJLRTZ": 13.67633083771,
   "EPSJB": 0.57,
   "XSMLL": 22.6079679267,
   "XSJLL": 6.6313178029,
   "ROEJQ": 11,
   "ROIC": 6.766240521296,
   "MGJYXJJE": 1.203299548343,
   "JYXJLYYSR": 0.140269184745,
   "ZCFZL": 64.0099309235
  },
  {
   "REPORT_DATE": "2025-09-30 00:00:00",
   "REPORT_TYPE": "三季报",
   "REPORT_DATE_NAME": "2025三季报",
   "NOTICE_DATE": "2025-10-31 00:00:00",
   "UPDATE_DATE": "2025-10-31 00:00:00",
   "TOTALOPERATEREVE": 78157334159.19,
   "TOTALOPERATEREVETZ": 11.606596994095,
   "PARENTNETPROFIT": 5977215500.11,
   "PARENTNETPROFITTZ": 11.673607681842,
   "KCFJCXSYJLR": 6001748371.29,
   "KCFJCXSYJLRTZ": 22.763344071944,
   "EPSJB": 0.51,
   "XSMLL": 22.3260647554,
   "XSJLL": 7.7835736534,
   "ROEJQ": 9.92,
   "ROIC": 6.286462414041,
   "MGJYXJJE": 0.484273237174,
   "JYXJLYYSR": 0.072822980613,
   "ZCFZL": 65.8555632935
  },
  {
   "REPORT_DATE": "2025-06-30 00:00:00",
   "REPORT_TYPE": "中报",
   "REPORT_DATE_NAME": "2025中报",
   "NOTICE_DATE": "2025-08-30 00:00:00",
   "UPDATE_DATE": "2025-08-30 00:00:00",
   "TOTALOPERATEREVE": 54808231312.22,
   "TOTALOPERATEREVETZ": 8.038204223536,
   "PARENTNETPROFIT": 4358409242.35,
   "PARENTNETPROFITTZ": 16.626569636167,
   "KCFJCXSYJLR": 4466711196.71,
   "KCFJCXSYJLRTZ": 35.574839212286,
   "EPSJB": 0.37,
   "XSMLL": 22.0293547943,
   "XSJLL": 8.0584507424,
   "ROEJQ": 7.15,
   "ROIC": 4.636436131426,
   "MGJYXJJE": 0.316925267934,
   "JYXJLYYSR": 0.067965147644,
   "ZCFZL": 64.9201787386
  },
  {
   "REPORT_DATE": "2025-03-31 00:00:00",
   "REPORT_TYPE": "一季报",
   "REPORT_DATE_NAME": "2025一季报",
   "NOTICE_DATE": "2025-04-29 00:00:00",
   "UPDATE_DATE": "2026-04-29 00:00:00",
   "TOTALOPERATEREVE": 27266147629.96,
   "TOTALOPERATEREVETZ": 12.789253689477,
   "PARENTNETPROFIT": 2038858424.57,
   "PARENTNETPROFITTZ": 27.391089385959,
   "KCFJCXSYJLR": 2007366625.56,
   "KCFJCXSYJLRTZ": 36.883164881906,
   "EPSJB": 0.172,
   "XSMLL": 21.9478794806,
   "XSJLL": 7.5657272653,
   "ROEJQ": 3.37,
   "ROIC": 2.20425752543,
   "MGJYXJJE": 0.071986368779,
   "JYXJLYYSR": 0.031180629371,
   "ZCFZL": 63.5702880577
  },
  {
   "REPORT_DATE": "2024-12-31 00:00:00",
   "REPORT_TYPE": "年报",
   "REPORT_DATE_NAME": "2024年报",
   "NOTICE_DATE": "2025-04-29 00:00:00",
   "UPDATE_DATE": "2026-04-29 00:00:00",
   "TOTALOPERATEREVE": 93037413551.56,
   "TOTALOPERATEREVETZ": 0.203765940378,
   "PARENTNETPROFIT": 6031810430.92,
   "PARENTNETPROFITTZ": 13.242167959182,
   "KCFJCXSYJLR": 5762209959.1,
   "KCFJCXSYJLRTZ": 28.139263383412,
   "EPSJB": 0.51,
   "XSMLL": 22.5693692839,
   "XSJLL": 6.5369178797,
   "ROEJQ": 10.37,
   "ROIC": 6.801831481484,
   "MGJYXJJE": 0.481781279784,
   "JYXJLYYSR": 0.061188369336,
   "ZCFZL": 62.7652796495
  },
  {
   "REPORT_DATE": "2024-09-30 00:00:00",
   "REPORT_TYPE": "三季报",
   "REPORT_DATE_NAME": "2024三季报",
   "NOTICE_DATE": "2024-10-31 00:00:00",
   "UPDATE_DATE": "2025-10-31 00:00:00",
   "TOTALOPERATEREVE": 70029313915.31,
   "TOTALOPERATEREVETZ": -2.28940799888,
   "PARENTNETPROFIT": 5352397602.43,
   "PARENTNETPROFITTZ": 10.602241409301,
   "KCFJCXSYJLR": 4888876575.22,
   "KCFJCXSYJLRTZ": 11.850500352855,
   "EPSJB": 0.45,
   "XSMLL": 21.9694271397,
   "XSJLL": 7.7425051309,
   "ROEJQ": 9.19,
   "ROIC": 5.795910447223,
   "MGJYXJJE": 0.155148524774,
   "JYXJLYYSR": 0.026178476345,
   "ZCFZL": 63.8398223361
  },
  {
   "REPORT_DATE": "2024-06-30 00:00:00",
   "REPORT_TYPE": "中报",
   "REPORT_DATE_NAME": "2024中报",
   "NOTICE_DATE": "2024-08-29 00:00:00",
   "UPDATE_DATE": "2025-08-30 00:00:00",
   "TOTALOPERATEREVE": 50730416805.91,
   "TOTALOPERATEREVETZ": -1.067163286689,
   "PARENTNETPROFIT": 3737063737.66,
   "PARENTNETPROFITTZ": 4.112442582235,
   "KCFJCXSYJLR": 3294646132.47,
   "KCFJCXSYJLRTZ": -2.349939362927,
   "EPSJB": 0.32,
   "XSMLL": 21.3290232273,
   "XSJLL": 7.4801528756,
   "ROEJQ": 6.43,
   "ROIC": 4.183658183526,
   "MGJYXJJE": 0.151884817973,
   "JYXJLYYSR": 0.035377123808,
   "ZCFZL": 63.2749849224
  },
  {
   "REPORT_DATE": "2024-03-31 00:00:00",
   "REPORT_TYPE": "一季报",
   "REPORT_DATE_NAME": "2024一季报",
   "NOTICE_DATE": "2024-04-30 00:00:00",
   "UPDATE_DATE": "2025-04-29 00:00:00",
   "TOTALOPERATEREVE": 24174419759.02,
   "TOTALOPERATEREVETZ": 1.178219101211,
   "PARENTNETPROFIT": 1600471771.14,
   "PARENTNETPROFITTZ": 5.062602849355,
   "KCFJCXSYJLR": 1466481745.43,
   "KCFJCXSYJLRTZ": 12.479385557339,
   "EPSJB": 0.135,
   "XSMLL": 21.5610016955,
   "XSJLL": 6.6275695878,
   "ROEJQ": 2.81,
   "ROIC": 1.857453702726,
   "MGJYXJJE": 0.019570780184,
   "JYXJLYYSR": 0.009565962349,
   "ZCFZL": 64.0065160211
  },
  {
   "REPORT_DATE": "2023-12-31 00:00:00",
   "REPORT_TYPE": "年报",
   "REPORT_DATE_NAME": "2023年报",
   "NOTICE_DATE": "2024-04-30 00:00:00",
   "UPDATE_DATE": "2025-04-29 00:00:00",
   "TOTALOPERATEREVE": 92848220501.93,
   "TOTALOPERATEREVETZ": -1.032755926573,
   "PARENTNETPROFIT": 5326470288.96,
   "PARENTNETPROFITTZ": 23.51407401551,
   "KCFJCXSYJLR": 4496833996.82,
   "KCFJCXSYJLRTZ": 29.465082409025,
   "EPSJB": 0.45,
   "XSMLL": 20.8030602225,
   "XSJLL": 5.6394150116,
   "ROEJQ": 9.83,
   "ROIC": 6.167562433734,
   "MGJYXJJE": 0.302205757478,
   "JYXJLYYSR": 0.038459686199,
   "ZCFZL": 64.5130254085
  },
  {
   "REPORT_DATE": "2023-09-30 00:00:00",
   "REPORT_TYPE": "三季报",
   "REPORT_DATE_NAME": "2023三季报",
   "NOTICE_DATE": "2023-10-31 00:00:00",
   "UPDATE_DATE": "2024-10-31 00:00:00",
   "TOTALOPERATEREVE": 71670135735.65,
   "TOTALOPERATEREVETZ": -4.580154511047,
   "PARENTNETPROFIT": 4839321097.14,
   "PARENTNETPROFITTZ": 3.495388619836,
   "KCFJCXSYJLR": 4370902731.59,
   "KCFJCXSYJLRTZ": -7.389088936199,
   "EPSJB": 0.41,
   "XSMLL": 22.9010186102,
   "XSJLL": 6.7112717154,
   "ROEJQ": 8.84,
   "ROIC": 5.655236295229,
   "MGJYXJJE": 0.13897489404,
   "JYXJLYYSR": 0.022912617841,
   "ZCFZL": 65.2420424837
  },
  {
   "REPORT_DATE": "2023-06-30 00:00:00",
   "REPORT_TYPE": "中报",
   "REPORT_DATE_NAME": "2023中报",
   "NOTICE_DATE": "2023-08-31 00:00:00",
   "UPDATE_DATE": "2024-08-29 00:00:00",
   "TOTALOPERATEREVE": 51277632878.27,
   "TOTALOPERATEREVETZ": -4.775626818364,
   "PARENTNETPROFIT": 3589449680.53,
   "PARENTNETPROFITTZ": -2.10010036305,
   "KCFJCXSYJLR": 3373931476.31,
   "KCFJCXSYJLRTZ": -6.792796276786,
   "EPSJB": 0.3,
   "XSMLL": 22.8585344173,
   "XSJLL": 6.8512208856,
   "ROEJQ": 6.7,
   "ROIC": 4.033322914252,
   "MGJYXJJE": 0.130108616693,
   "JYXJLYYSR": 0.029981591167,
   "ZCFZL": 67.4454424301
  },
  {
   "REPORT_DATE": "2023-03-31 00:00:00",
   "REPORT_TYPE": "一季报",
   "REPORT_DATE_NAME": "2023一季报",
   "NOTICE_DATE": "2023-04-29 00:00:00",
   "UPDATE_DATE": "2024-04-30 00:00:00",
   "TOTALOPERATEREVE": 23892908942.03,
   "TOTALOPERATEREVETZ": -9.811266938666,
   "PARENTNETPROFIT": 1523350581.21,
   "PARENTNETPROFITTZ": -26.37691397986,
   "KCFJCXSYJLR": 1303778232.93,
   "KCFJCXSYJLRTZ": 0.394365331601,
   "EPSJB": 0.129,
   "XSMLL": 22.8391428846,
   "XSJLL": 6.4998760862,
   "ROEJQ": 2.84,
   "ROIC": 1.837063863308,
   "MGJYXJJE": 0.068126680055,
   "JYXJLYYSR": 0.033691844256,
   "ZCFZL": 68.3892347982
  },
  {
   "REPORT_DATE": "2022-12-31 00:00:00",
   "REPORT_TYPE": "年报",
   "REPORT_DATE_NAME": "2022年报",
   "NOTICE_DATE": "2023-04-29 00:00:00",
   "UPDATE_DATE": "2024-04-30 00:00:00",
   "TOTALOPERATEREVE": 93817122393.59,
   "TOTALOPERATEREVETZ": -19.674503511337,
   "PARENTNETPROFIT": 4312439963.96,
   "PARENTNETPROFITTZ": -47.460257219848,
   "KCFJCXSYJLR": 3473395229.93,
   "KCFJCXSYJLRTZ": -52.981460373632,
   "EPSJB": 0.36,
   "XSMLL": 20.2116211531,
   "XSJLL": 4.5851723236,
   "ROEJQ": 8.14,
   "ROIC": 5.137648374873,
   "MGJYXJJE": 0.133960866007,
   "JYXJLYYSR": 0.01687222761,
   "ZCFZL": 68.7930943202
  },
  {
   "REPORT_DATE": "2022-09-30 00:00:00",
   "REPORT_TYPE": "三季报",
   "REPORT_DATE_NAME": "2022三季报",
   "NOTICE_DATE": "2022-10-26 00:00:00",
   "UPDATE_DATE": "2023-10-31 00:00:00",
   "TOTALOPERATEREVE": 75110303698.77,
   "TOTALOPERATEREVETZ": -19.817235591394,
   "PARENTNETPROFIT": 4675880888.68,
   "PARENTNETPROFITTZ": -31.329829587548,
   "KCFJCXSYJLR": 4719641218.71,
   "KCFJCXSYJLRTZ": -24.023699065713,
   "EPSJB": 0.4,
   "XSMLL": 20.2154716336,
   "XSJLL": 6.3234228147,
   "ROEJQ": 8.7,
   "ROIC": 5.655397560075,
   "MGJYXJJE": 0.131472739436,
   "JYXJLYYSR": 0.020698467123,
   "ZCFZL": 69.0614036586
  },
  {
   "REPORT_DATE": "2022-06-30 00:00:00",
   "REPORT_TYPE": "中报",
   "REPORT_DATE_NAME": "2022中报",
   "NOTICE_DATE": "2022-08-31 00:00:00",
   "UPDATE_DATE": "2023-08-31 00:00:00",
   "TOTALOPERATEREVE": 53849273211.24,
   "TOTALOPERATEREVETZ": 1.15612484385,
   "PARENTNETPROFIT": 3666448784.77,
   "PARENTNETPROFITTZ": -3.591669325691,
   "KCFJCXSYJLR": 3619818363.32,
   "KCFJCXSYJLRTZ": -0.272692158307,
   "EPSJB": 0.31,
   "XSMLL": 20.4138173444,
   "XSJLL": 6.8846933532,
   "ROEJQ": 6.87,
   "ROIC": 5.134736362904,
   "MGJYXJJE": 0.371262146372,
   "JYXJLYYSR": 0.054008984372,
   "ZCFZL": 66.6130423473
  },
  {
   "REPORT_DATE": "2022-03-31 00:00:00",
   "REPORT_TYPE": "一季报",
   "REPORT_DATE_NAME": "2022一季报",
   "NOTICE_DATE": "2022-04-30 00:00:00",
   "UPDATE_DATE": "2023-04-29 00:00:00",
   "TOTALOPERATEREVE": 26492121721.88,
   "TOTALOPERATEREVETZ": 6.063574270395,
   "PARENTNETPROFIT": 2069120792.89,
   "PARENTNETPROFITTZ": 19.828032678342,
   "KCFJCXSYJLR": 1298656780.81,
   "KCFJCXSYJLRTZ": -18.208320555447,
   "EPSJB": 0.175,
   "XSMLL": 21.3247226532,
   "XSJLL": 7.886657986,
   "ROEJQ": 3.94,
   "ROIC": 3.02050816161,
   "MGJYXJJE": 0.140457662191,
   "JYXJLYYSR": 0.041533055208,
   "ZCFZL": 66.5375007645
  },
  {
   "REPORT_DATE": "2021-12-31 00:00:00",
   "REPORT_TYPE": "年报",
   "REPORT_DATE_NAME": "2021年报",
   "NOTICE_DATE": "2022-04-19 00:00:00",
   "UPDATE_DATE": "2023-04-29 00:00:00",
   "TOTALOPERATEREVE": 116796193605.64,
   "TOTALOPERATEREVETZ": 57.900658423921,
   "PARENTNETPROFIT": 8207957892,
   "PARENTNETPROFITTZ": 120.119786503219,
   "KCFJCXSYJLR": 7387288626,
   "KCFJCXSYJLRTZ": 73.94279753347,
   "EPSJB": 0.69,
   "XSMLL": 21.4615055272,
   "XSJLL": 7.0751902551,
   "ROEJQ": 15.91,
   "ROIC": 12.20409710438,
   "MGJYXJJE": 1.458190105524,
   "JYXJLYYSR": 0.097802654709,
   "ZCFZL": 68.4080376772
  },
  {
   "REPORT_DATE": "2021-09-30 00:00:00",
   "REPORT_TYPE": "三季报",
   "REPORT_DATE_NAME": "2021三季报",
   "NOTICE_DATE": "2021-10-30 00:00:00",
   "UPDATE_DATE": "2022-10-26 00:00:00",
   "TOTALOPERATEREVE": 93673876490.48,
   "TOTALOPERATEREVETZ": 82.645005999426,
   "PARENTNETPROFIT": 6809187833.08,
   "PARENTNETPROFITTZ": 179.730320919224,
   "KCFJCXSYJLR": 6211991319.23,
   "KCFJCXSYJLRTZ": 156.985419910242,
   "EPSJB": 0.57,
   "XSMLL": 21.4784511796,
   "XSJLL": 7.307191571,
   "ROEJQ": 13.3,
   "ROIC": 14.447053276088,
   "MGJYXJJE": 0.999230181633,
   "JYXJLYYSR": 0.083577148764,
   "ZCFZL": 63.6867569326
  },
  {
   "REPORT_DATE": "2021-06-30 00:00:00",
   "REPORT_TYPE": "中报",
   "REPORT_DATE_NAME": "2021中报",
   "NOTICE_DATE": "2021-08-31 00:00:00",
   "UPDATE_DATE": "2022-08-31 00:00:00",
   "TOTALOPERATEREVE": 53233823749.54,
   "TOTALOPERATEREVETZ": 51.798444417661,
   "PARENTNETPROFIT": 3803041458.27,
   "PARENTNETPROFITTZ": 84.458277619066,
   "KCFJCXSYJLR": 3629716315.08,
   "KCFJCXSYJLRTZ": 79.204773444347,
   "EPSJB": 0.4794,
   "XSMLL": 15.803244776,
   "XSJLL": 7.1942679727,
   "ROEJQ": 11.19,
   "ROIC": 7.657716445561,
   "MGJYXJJE": 0.478828946045,
   "JYXJLYYSR": 0.070462479187,
   "ZCFZL": 64.5943335242
  },
  {
   "REPORT_DATE": "2021-03-31 00:00:00",
   "REPORT_TYPE": "一季报",
   "REPORT_DATE_NAME": "2021一季报",
   "NOTICE_DATE": "2021-04-30 00:00:00",
   "UPDATE_DATE": "2022-04-30 00:00:00",
   "TOTALOPERATEREVE": 24977587172.71,
   "TOTALOPERATEREVETZ": 80.398002311137,
   "PARENTNETPROFIT": 1726741853.84,
   "PARENTNETPROFITTZ": 182.437919609911,
   "KCFJCXSYJLR": 1587761480.91,
   "KCFJCXSYJLRTZ": 182.20008193016,
   "EPSJB": 0.217,
   "XSMLL": 16.5791890452,
   "XSJLL": 6.9883563323,
   "ROEJQ": 5.23,
   "ROIC": 3.704910601255,
   "MGJYXJJE": 0.248373379056,
   "JYXJLYYSR": 0.077896823456,
   "ZCFZL": 62.7999661207
  },
  {
   "REPORT_DATE": "2020-12-31 00:00:00",
   "REPORT_TYPE": "年报",
   "REPORT_DATE_NAME": "2020年报",
   "NOTICE_DATE": "2021-04-30 00:00:00",
   "UPDATE_DATE": "2022-04-19 00:00:00",
   "TOTALOPERATEREVE": 73968148563.43,
   "TOTALOPERATEREVETZ": 24.996873589941,
   "PARENTNETPROFIT": 3728859646.1,
   "PARENTNETPROFITTZ": 2.990885616189,
   "KCFJCXSYJLR": 4246964364.58,
   "KCFJCXSYJLRTZ": 21.882948321725,
   "EPSJB": 0.4505,
   "XSMLL": 17.0708908564,
   "XSJLL": 5.0639139847,
   "ROEJQ": 9.9,
   "ROIC": 8.292841012035,
   "MGJYXJJE": 0.356051876885,
   "JYXJLYYSR": 0.037708018946,
   "ZCFZL": 62.7759185642
  },
  {
   "REPORT_DATE": "2020-09-30 00:00:00",
   "REPORT_TYPE": "三季报",
   "REPORT_DATE_NAME": "2020三季报",
   "NOTICE_DATE": "2020-10-31 00:00:00",
   "UPDATE_DATE": "2021-10-30 00:00:00",
   "TOTALOPERATEREVE": 51287400921.75,
   "TOTALOPERATEREVETZ": 18.614175957434,
   "PARENTNETPROFIT": 2434197269.25,
   "PARENTNETPROFITTZ": -19.397787266847,
   "KCFJCXSYJLR": 2417254380.19,
   "KCFJCXSYJLRTZ": -11.226471330679,
   "EPSJB": 0.288,
   "XSMLL": 18.0213575196,
   "XSJLL": 4.765542591,
   "ROEJQ": 7.67,
   "ROIC": 5.406906074342,
   "MGJYXJJE": 0.089490291465,
   "JYXJLYYSR": 0.013668800884,
   "ZCFZL": 62.5887993611
  },
  {
   "REPORT_DATE": "2020-06-30 00:00:00",
   "REPORT_TYPE": "中报",
   "REPORT_DATE_NAME": "2020中报",
   "NOTICE_DATE": "2020-08-31 00:00:00",
   "UPDATE_DATE": "2021-08-31 00:00:00",
   "TOTALOPERATEREVE": 35068754461.72,
   "TOTALOPERATEREVETZ": 12.558066145568,
   "PARENTNETPROFIT": 2061735318.88,
   "PARENTNETPROFITTZ": -9.703982424158,
   "KCFJCXSYJLR": 2025457383.37,
   "KCFJCXSYJLRTZ": -7.050052053381,
   "EPSJB": 0.248,
   "XSMLL": 18.3065117945,
   "XSJLL": 5.9106244135,
   "ROEJQ": 6.6,
   "ROIC": 4.588280397229,
   "MGJYXJJE": 0.063965116323,
   "JYXJLYYSR": 0.014288546031,
   "ZCFZL": 60.2276869462
  },
  {
   "REPORT_DATE": "2020-03-31 00:00:00",
   "REPORT_TYPE": "一季报",
   "REPORT_DATE_NAME": "2020一季报",
   "NOTICE_DATE": "2020-04-30 00:00:00",
   "UPDATE_DATE": "2021-04-30 00:00:00",
   "TOTALOPERATEREVE": 13845822488.45,
   "TOTALOPERATEREVETZ": -3.978537167788,
   "PARENTNETPROFIT": 611370405.3,
   "PARENTNETPROFITTZ": -41.947425144704,
   "KCFJCXSYJLR": 562636789.49,
   "KCFJCXSYJLRTZ": -40.58129542954,
   "EPSJB": 0.07,
   "XSMLL": 18.3073593627,
   "XSJLL": 4.4701630142,
   "ROEJQ": 1.91,
   "ROIC": 1.357523659794,
   "MGJYXJJE": 0.01549454721,
   "JYXJLYYSR": 0.008766481401,
   "ZCFZL": 58.9458380506
  },
  {
   "REPORT_DATE": "2019-12-31 00:00:00",
   "REPORT_TYPE": "年报",
   "REPORT_DATE_NAME": "2019年报",
   "NOTICE_DATE": "2020-04-30 00:00:00",
   "UPDATE_DATE": "2021-04-30 00:00:00",
   "TOTALOPERATEREVE": 59175998918.25,
   "TOTALOPERATEREVETZ": 33.249248799458,
   "PARENTNETPROFIT": 3620572465.02,
   "PARENTNETPROFITTZ": 76.981615485207,
   "KCFJCXSYJLR": 3484461463.28,
   "KCFJCXSYJLRTZ": 94.77626780322,
   "EPSJB": 0.432,
   "XSMLL": 17.4531916471,
   "XSJLL": 6.1602284627,
   "ROEJQ": 12.56,
   "ROIC": 8.821983894587,
   "MGJYXJJE": 0.655579702626,
   "JYXJLYYSR": 0.086785083711,
   "ZCFZL": 56.4685380812
  },
  {
   "REPORT_DATE": "2019-09-30 00:00:00",
   "REPORT_TYPE": "三季报",
   "REPORT_DATE_NAME": "2019三季报",
   "NOTICE_DATE": "2019-10-31 00:00:00",
   "UPDATE_DATE": "2020-10-31 00:00:00",
   "TOTALOPERATEREVE": 43238846038.23,
   "TOTALOPERATEREVETZ": 26.889975586877,
   "PARENTNETPROFIT": 3020012958.34,
   "PARENTNETPROFITTZ": 100.279206105402,
   "KCFJCXSYJLR": 2722945022.49,
   "KCFJCXSYJLRTZ": 99.239096825665,
   "EPSJB": 0.363,
   "XSMLL": 18.566795263,
   "XSJLL": 7.0173399922,
   "ROEJQ": 10.63,
   "ROIC": 7.437829785791,
   "MGJYXJJE": 0.395945459705,
   "JYXJLYYSR": 0.0717342328,
   "ZCFZL": 52.6187867621
  },
  {
   "REPORT_DATE": "2019-06-30 00:00:00",
   "REPORT_TYPE": "中报",
   "REPORT_DATE_NAME": "2019中报",
   "NOTICE_DATE": "2019-08-31 00:00:00",
   "UPDATE_DATE": "2020-08-31 00:00:00",
   "TOTALOPERATEREVE": 31156145145.89,
   "TOTALOPERATEREVETZ": 30.121154258358,
   "PARENTNETPROFIT": 2283307031.95,
   "PARENTNETPROFITTZ": 106.815642058519,
   "KCFJCXSYJLR": 2179083935.08,
   "KCFJCXSYJLRTZ": 115.541018129753,
   "EPSJB": 0.276,
   "XSMLL": 18.3333848226,
   "XSJLL": 7.3566890524,
   "ROEJQ": 8.15,
   "ROIC": 5.532936209708,
   "MGJYXJJE": 0.36262673616,
   "JYXJLYYSR": 0.091176158078,
   "ZCFZL": 53.8370280989
  },
  {
   "REPORT_DATE": "2019-03-31 00:00:00",
   "REPORT_TYPE": "一季报",
   "REPORT_DATE_NAME": "2019一季报",
   "NOTICE_DATE": "2019-04-30 00:00:00",
   "UPDATE_DATE": "2020-04-30 00:00:00",
   "TOTALOPERATEREVE": 14419507972.55,
   "TOTALOPERATEREVETZ": 33.715950484583,
   "PARENTNETPROFIT": 1053132280.22,
   "PARENTNETPROFITTZ": 102.735025911253,
   "KCFJCXSYJLR": 946901810.73,
   "KCFJCXSYJLRTZ": 92.33649061738,
   "EPSJB": 0.128,
   "XSMLL": 16.7579964625,
   "XSJLL": 7.3379647803,
   "ROEJQ": 3.86,
   "ROIC": 2.602489554691,
   "MGJYXJJE": 0.01361033614,
   "JYXJLYYSR": 0.00739407064,
   "ZCFZL": 52.480368471
  },
  {
   "REPORT_DATE": "2018-12-31 00:00:00",
   "REPORT_TYPE": "年报",
   "REPORT_DATE_NAME": "2018年报",
   "NOTICE_DATE": "2019-04-30 00:00:00",
   "UPDATE_DATE": "2020-04-30 00:00:00",
   "TOTALOPERATEREVE": 44410005648.37,
   "TOTALOPERATEREVETZ": 52.448752696261,
   "PARENTNETPROFIT": 2045733651.54,
   "PARENTNETPROFITTZ": 100.440732190548,
   "KCFJCXSYJLR": 1788955863.35,
   "KCFJCXSYJLRTZ": 115.73113724922,
   "EPSJB": 0.261,
   "XSMLL": 16.6889394329,
   "XSJLL": 4.628802027,
   "ROEJQ": 8.28,
   "ROIC": 5.716892905423,
   "MGJYXJJE": 0.422370787083,
   "JYXJLYYSR": 0.074503766713,
   "ZCFZL": 50.4643766967
  },
  {
   "REPORT_DATE": "2018-09-30 00:00:00",
   "REPORT_TYPE": "三季报",
   "REPORT_DATE_NAME": "2018三季报",
   "NOTICE_DATE": "2018-10-31 00:00:00",
   "UPDATE_DATE": "2019-10-31 00:00:00",
   "TOTALOPERATEREVE": 34075856534.96,
   "TOTALOPERATEREVETZ": 58.166599338646,
   "PARENTNETPROFIT": 1507901402.78,
   "PARENTNETPROFITTZ": 93.854547006118,
   "KCFJCXSYJLR": 1366672036.7,
   "KCFJCXSYJLRTZ": 102.839087696506,
   "EPSJB": 0.195,
   "XSMLL": 17.9206514842,
   "XSJLL": 4.4372795665,
   "ROEJQ": 6.38,
   "ROIC": 4.479088823435,
   "MGJYXJJE": 0.245191013558,
   "JYXJLYYSR": 0.056366744597,
   "ZCFZL": 52.512908811
  },
  {
   "REPORT_DATE": "2018-06-30 00:00:00",
   "REPORT_TYPE": "中报",
   "REPORT_DATE_NAME": "2018中报",
   "NOTICE_DATE": "2018-08-31 00:00:00",
   "UPDATE_DATE": "2019-08-31 00:00:00",
   "TOTALOPERATEREVE": 23943950792.22,
   "TOTALOPERATEREVETZ": 65.810981513622,
   "PARENTNETPROFIT": 1104030144.54,
   "PARENTNETPROFITTZ": 100.620496146193,
   "KCFJCXSYJLR": 1010983410.02,
   "KCFJCXSYJLRTZ": 111.553000765632,
   "EPSJB": 0.147,
   "XSMLL": 17.3369384465,
   "XSJLL": 4.6273883157,
   "ROEJQ": 4.73,
   "ROIC": 3.262054811835,
   "MGJYXJJE": 0.277698017371,
   "JYXJLYYSR": 0.081274476921,
   "ZCFZL": 54.0960214122
  },
  {
   "REPORT_DATE": "2018-03-31 00:00:00",
   "REPORT_TYPE": "一季报",
   "REPORT_DATE_NAME": "2018一季报",
   "NOTICE_DATE": "2018-04-28 00:00:00",
   "UPDATE_DATE": "2019-04-30 00:00:00",
   "TOTALOPERATEREVE": 10783685805.84,
   "TOTALOPERATEREVETZ": 79.790976580574,
   "PARENTNETPROFIT": 519462424.16,
   "PARENTNETPROFITTZ": 157.390462048526,
   "KCFJCXSYJLR": 492315216.78,
   "KCFJCXSYJLRTZ": 205.67071970686,
   "EPSJB": 0.07,
   "XSMLL": 18.1120004287,
   "XSJLL": 4.8591487963,
   "ROEJQ": 2.23,
   "ROIC": 1.645968630362,
   "MGJYXJJE": 0.103063030126,
   "JYXJLYYSR": 0.066975026853,
   "ZCFZL": 53.7120127172
  },
  {
   "REPORT_DATE": "2017-12-31 00:00:00",
   "REPORT_TYPE": "年报",
   "REPORT_DATE_NAME": "2017年报",
   "NOTICE_DATE": "2018-04-28 00:00:00",
   "UPDATE_DATE": "2019-04-30 00:00:00",
   "TOTALOPERATEREVE": 29131104625.6,
   "TOTALOPERATEREVETZ": 72.462897956411,
   "PARENTNETPROFIT": 1020617730.33,
   "PARENTNETPROFITTZ": 389.309626305959,
   "KCFJCXSYJLR": 829252506.69,
   "KCFJCXSYJLRTZ": 13463.0606190655,
   "EPSJB": 0.14,
   "XSMLL": 18.8869162644,
   "XSJLL": 3.5314904807,
   "ROEJQ": 4.7,
   "ROIC": 3.432069612228,
   "MGJYXJJE": 0.449990559613,
   "JYXJLYYSR": 0.10824894317,
   "ZCFZL": 51.6661189396
  },
  {
   "REPORT_DATE": "2017-09-30 00:00:00",
   "REPORT_TYPE": "三季报",
   "REPORT_DATE_NAME": "2017三季报",
   "NOTICE_DATE": "2017-10-31 00:00:00",
   "UPDATE_DATE": "2018-10-31 00:00:00",
   "TOTALOPERATEREVE": 21544280952.77,
   "TOTALOPERATEREVETZ": 78.197631890428,
   "PARENTNETPROFIT": 777851964.82,
   "PARENTNETPROFITTZ": 370.385282536004,
   "KCFJCXSYJLR": 673771535.96,
   "KCFJCXSYJLRTZ": 13849.0269792507,
   "EPSJB": 0.111,
   "XSMLL": 20.0203582705,
   "XSJLL": 3.6327457075,
   "ROEJQ": 3.73,
   "ROIC": 2.931057927994,
   "MGJYXJJE": 0.316831066903,
   "JYXJLYYSR": 0.103055926274,
   "ZCFZL": 52.8509155508
  },
  {
   "REPORT_DATE": "2017-06-30 00:00:00",
   "REPORT_TYPE": "中报",
   "REPORT_DATE_NAME": "2017中报",
   "NOTICE_DATE": "2017-08-31 00:00:00",
   "UPDATE_DATE": "2018-08-31 00:00:00",
   "TOTALOPERATEREVE": 14440509653.61,
   "TOTALOPERATEREVETZ": 77.435070300727,
   "PARENTNETPROFIT": 550307753.07,
   "PARENTNETPROFITTZ": 333.270151599124,
   "KCFJCXSYJLR": 477886584.62,
   "KCFJCXSYJLRTZ": 2306.87177172,
   "EPSJB": 0.079,
   "XSMLL": 19.1335570073,
   "XSJLL": 3.8246449658,
   "ROEJQ": 2.66,
   "ROIC": 1.93716702099,
   "MGJYXJJE": 0.237640949794,
   "JYXJLYYSR": 0.115323011152,
   "ZCFZL": 54.1422401227
  },
  {
   "REPORT_DATE": "2017-03-31 00:00:00",
   "REPORT_TYPE": "一季报",
   "REPORT_DATE_NAME": "2017一季报",
   "NOTICE_DATE": "2017-04-29 00:00:00",
   "UPDATE_DATE": "2018-04-28 00:00:00",
   "TOTALOPERATEREVE": 5997901569.33,
   "TOTALOPERATEREVETZ": 72.470362202143,
   "PARENTNETPROFIT": 201818831.99,
   "PARENTNETPROFITTZ": 1809.98213631124,
   "KCFJCXSYJLR": 161060639.78,
   "KCFJCXSYJLRTZ": 633.460654466466,
   "EPSJB": 0.029,
   "XSMLL": 17.7444223542,
   "XSJLL": 3.3598835281,
   "ROEJQ": 0.98,
   "ROIC": 0.89421860874,
   "MGJYXJJE": 0.098695864597,
   "JYXJLYYSR": 0.115312619218,
   "ZCFZL": 54.4735217468
  },
  {
   "REPORT_DATE": "2016-12-31 00:00:00",
   "REPORT_TYPE": "年报",
   "REPORT_DATE_NAME": "2016年报",
   "NOTICE_DATE": "2017-03-25 00:00:00",
   "UPDATE_DATE": "2018-04-28 00:00:00",
   "TOTALOPERATEREVE": 16891229922.95,
   "TOTALOPERATEREVETZ": 1.170645043444,
   "PARENTNETPROFIT": 208583211.01,
   "PARENTNETPROFITTZ": 268.04639037334,
   "KCFJCXSYJLR": -6205558.22,
   "KCFJCXSYJLRTZ": 99.270892595331,
   "EPSJB": 0.03,
   "XSMLL": 19.4423783069,
   "XSJLL": 1.2822660917,
   "ROEJQ": 1.01,
   "ROIC": 1.55570846539,
   "MGJYXJJE": 0.320409189269,
   "JYXJLYYSR": 0.132929357235,
   "ZCFZL": 53.426660705
  },
  {
   "REPORT_DATE": "2016-09-30 00:00:00",
   "REPORT_TYPE": "三季报",
   "REPORT_DATE_NAME": "2016三季报",
   "NOTICE_DATE": "2016-10-31 00:00:00",
   "UPDATE_DATE": "2017-10-31 00:00:00",
   "TOTALOPERATEREVE": 12090105084.01,
   "TOTALOPERATEREVETZ": -7.450281140968,
   "PARENTNETPROFIT": 165364860.19,
   "PARENTNETPROFITTZ": 779.307344774346,
   "KCFJCXSYJLR": -4900503.41,
   "KCFJCXSYJLRTZ": 98.594155980913,
   "EPSJB": 0.024,
   "XSMLL": 20.2962406199,
   "XSJLL": 1.4187861248,
   "ROEJQ": 0.8,
   "ROIC": 0.826854582895,
   "MGJYXJJE": 0.225272052363,
   "JYXJLYYSR": 0.130573322587,
   "ZCFZL": 53.9637927689
  },
  {
   "REPORT_DATE": "2016-06-30 00:00:00",
   "REPORT_TYPE": "中报",
   "REPORT_DATE_NAME": "2016中报",
   "NOTICE_DATE": "2016-08-12 00:00:00",
   "UPDATE_DATE": "2017-08-31 00:00:00",
   "TOTALOPERATEREVE": 8138475459.86,
   "TOTALOPERATEREVETZ": -14.401695653211,
   "PARENTNETPROFIT": 127012615.81,
   "PARENTNETPROFITTZ": 1214.7707939094,
   "KCFJCXSYJLR": 19855091.17,
   "KCFJCXSYJLRTZ": 107.666948383758,
   "EPSJB": 0.018,
   "XSMLL": 19.9814054982,
   "XSJLL": 1.6156966256,
   "ROEJQ": 0.62,
   "ROIC": 1.143108990067,
   "MGJYXJJE": 0.076610925087,
   "JYXJLYYSR": 0.065966715887,
   "ZCFZL": 53.4624357609
  }
 ],
 "valuation_band": {
  "window_start": "2021-05-17 00:00:00",
  "window_end": "2026-07-10 00:00:00",
  "current_pe_ttm": 14.98155355,
  "current_pb": 1.57551821,
  "current_ps_ttm": 0.95527874,
  "current_pcf": 6.39243143,
  "pe_ttm_pct_rank": 39.8,
  "pe_ttm_min": 4.74431934,
  "pe_ttm_median": 16.01,
  "pe_ttm_max": 25.18483685,
  "pb_pct_rank": 69.4,
  "pb_min": 0.64830242,
  "pb_median": 1.46,
  "pb_max": 2.46006925
 },
 "performance_predicts": [
  {
   "REPORT_DATE": "2021-12-31 00:00:00",
   "NOTICE_DATE": "2022-01-26 00:00:00",
   "PREDICT_FINANCE_CODE": "005",
   "PREDICT_TYPE": "预增",
   "PREDICT_AMT_LOWER": 5000000000,
   "PREDICT_AMT_UPPER": 5500000000,
   "ADD_AMP_LOWER": 41.88,
   "ADD_AMP_UPPER": 56.07,
   "PREDICT_CONTENT": "预计2021年1-12月扣除非经常性损益后的净利润盈利:500,000万元至550,000万元,同比上年增长:41.88%至56.07%。",
   "CHANGE_REASON_EXPLAIN": "报告期内,公司营业收入继续稳步增长,盈利水平大幅提高。公司全面贯彻高质量、高效率、高效益、可持续的“三高一可”高质量发展新理念,切实增强质量管控意识,提升技术创新能力,提高内部管理水平,积极布局海外市场,全面推进企业转型升级,徐工产品竞争力和品牌影响力不断提升。"
  },
  {
   "REPORT_DATE": "2021-12-31 00:00:00",
   "NOTICE_DATE": "2022-01-26 00:00:00",
   "PREDICT_FINANCE_CODE": "003",
   "PREDICT_TYPE": "预增",
   "PREDICT_AMT_LOWER": 0.691,
   "PREDICT_AMT_UPPER": 0.754,
   "ADD_AMP_LOWER": null,
   "ADD_AMP_UPPER": null,
   "PREDICT_CONTENT": "预计2021年1-12月每股收益盈利:0.691元至0.754元。",
   "CHANGE_REASON_EXPLAIN": "报告期内,公司营业收入继续稳步增长,盈利水平大幅提高。公司全面贯彻高质量、高效率、高效益、可持续的“三高一可”高质量发展新理念,切实增强质量管控意识,提升技术创新能力,提高内部管理水平,积极布局海外市场,全面推进企业转型升级,徐工产品竞争力和品牌影响力不断提升。"
  },
  {
   "REPORT_DATE": "2021-12-31 00:00:00",
   "NOTICE_DATE": "2022-01-26 00:00:00",
   "PREDICT_FINANCE_CODE": "004",
   "PREDICT_TYPE": "预增",
   "PREDICT_AMT_LOWER": 5500000000,
   "PREDICT_AMT_UPPER": 6000000000,
   "ADD_AMP_LOWER": 47.5,
   "ADD_AMP_UPPER": 60.91,
   "PREDICT_CONTENT": "预计2021年1-12月归属于上市公司股东的净利润盈利:550,000万元至600,000万元,同比上年增长:47.5%至60.91%。",
   "CHANGE_REASON_EXPLAIN": "报告期内,公司营业收入继续稳步增长,盈利水平大幅提高。公司全面贯彻高质量、高效率、高效益、可持续的“三高一可”高质量发展新理念,切实增强质量管控意识,提升技术创新能力,提高内部管理水平,积极布局海外市场,全面推进企业转型升级,徐工产品竞争力和品牌影响力不断提升。"
  },
  {
   "REPORT_DATE": "2021-09-30 00:00:00",
   "NOTICE_DATE": "2021-10-15 00:00:00",
   "PREDICT_FINANCE_CODE": "003",
   "PREDICT_TYPE": "预增",
   "PREDICT_AMT_LOWER": 0.566,
   "PREDICT_AMT_UPPER": 0.591,
   "ADD_AMP_LOWER": null,
   "ADD_AMP_UPPER": null,
   "PREDICT_CONTENT": "预计2021年1-9月每股收益盈利:0.566元至0.591元。",
   "CHANGE_REASON_EXPLAIN": "报告期内,公司经营业绩实现稳定的增长,盈利能力稳步提升。公司持续提升技术创新能力,全面贯彻发展新理念,强化质量意识,提高企业内部管理水平,将高质量发展落实到企业发展的各方面、全过程;公司紧抓发展机遇,加快全球产业布局,海外市场开拓进程明显加快。"
  },
  {
   "REPORT_DATE": "2021-09-30 00:00:00",
   "NOTICE_DATE": "2021-10-15 00:00:00",
   "PREDICT_FINANCE_CODE": "004",
   "PREDICT_TYPE": "预增",
   "PREDICT_AMT_LOWER": 4503040000,
   "PREDICT_AMT_UPPER": 4703040000,
   "ADD_AMP_LOWER": 84.99,
   "ADD_AMP_UPPER": 93.21,
   "PREDICT_CONTENT": "预计2021年1-9月归属于上市公司股东的净利润盈利:450,304万元至470,304万元,同比上年增长:84.99%至93.21%。",
   "CHANGE_REASON_EXPLAIN": "报告期内,公司经营业绩实现稳定的增长,盈利能力稳步提升。公司持续提升技术创新能力,全面贯彻发展新理念,强化质量意识,提高企业内部管理水平,将高质量发展落实到企业发展的各方面、全过程;公司紧抓发展机遇,加快全球产业布局,海外市场开拓进程明显加快。"
  },
  {
   "REPORT_DATE": "2021-06-30 00:00:00",
   "NOTICE_DATE": "2021-07-01 00:00:00",
   "PREDICT_FINANCE_CODE": "003",
   "PREDICT_TYPE": "预增",
   "PREDICT_AMT_LOWER": 0.453,
   "PREDICT_AMT_UPPER": 0.53,
   "ADD_AMP_LOWER": null,
   "ADD_AMP_UPPER": null,
   "PREDICT_CONTENT": "预计2021年1-6月每股收益盈利:0.4530元至0.5300元。",
   "CHANGE_REASON_EXPLAIN": "2021年以来,叠加设备更新需求及环保排放标准升级等因素,行业景气度持续向好。公司继续推进高质量、高效率、高效益、可持续的“三高一可”高质量发展理念,加大研发投入,不断提升智能制造水平。通过全面推进精细化管理,严控各项费用支出,营业收入再创新高,盈利能力进一步提升。"
  }
 ],
 "performance_express": [
  {
   "REPORT_DATE": "2020-12-31 00:00:00",
   "NOTICE_DATE": "2021-04-15 00:00:00",
   "UPDATE_DATE": "2021-04-15 00:00:00",
   "TOTAL_OPERATE_INCOME": 73968148600,
   "YSTZ": 24.996873690289,
   "PARENT_NETPROFIT": 3728912700,
   "JLRTBZCL": 2.992349966753,
   "WEIGHTAVG_ROE": 11.73,
   "BASIC_EPS": 0.45
  },
  {
   "REPORT_DATE": "2019-12-31 00:00:00",
   "NOTICE_DATE": "2021-04-15 00:00:00",
   "UPDATE_DATE": "2021-04-15 00:00:00",
   "TOTAL_OPERATE_INCOME": 59175998900,
   "YSTZ": 33.249248758364,
   "PARENT_NETPROFIT": 3620572500,
   "JLRTBZCL": 76.981617195107,
   "WEIGHTAVG_ROE": 12.56,
   "BASIC_EPS": 0.432
  },
  {
   "REPORT_DATE": "2018-12-31 00:00:00",
   "NOTICE_DATE": "2019-04-15 00:00:00",
   "UPDATE_DATE": "2019-04-15 00:00:00",
   "TOTAL_OPERATE_INCOME": 44410005600,
   "YSTZ": 52.448752664188,
   "PARENT_NETPROFIT": 2041682800,
   "JLRTBZCL": 100.043836198412,
   "WEIGHTAVG_ROE": 8.27,
   "BASIC_EPS": 0.26
  },
  {
   "REPORT_DATE": "2017-12-31 00:00:00",
   "NOTICE_DATE": "2019-04-15 00:00:00",
   "UPDATE_DATE": "2019-04-15 00:00:00",
   "TOTAL_OPERATE_INCOME": 29131104600,
   "YSTZ": 72.462898039177,
   "PARENT_NETPROFIT": 1020617700,
   "JLRTBZCL": 389.309637593056,
   "WEIGHTAVG_ROE": 4.7,
   "BASIC_EPS": 0.14
  }
 ],
 "profit_forecast": {
  "pjtj": [
   {
    "SECUCODE": "000425.SZ",
    "SECURITY_NAME_ABBR": "徐工机械",
    "SECURITY_INNER_CODE": "1000001764",
    "ORG_CODE": "10634817",
    "SECURITY_TYPE_CODE": "058001001",
    "TRADE_MARKET_CODE": "069001002001",
    "DATE_TYPE_CODE": 1,
    "DATE_TYPE": "1月内",
    "COMPRE_RATING_NUM": null,
    "COMPRE_RATING": null,
    "RATING_ORG_NUM": null,
    "RATING_BUY_NUM": null,
    "RATING_ADD_NUM": null,
    "RATING_NEUTRAL_NUM": null,
    "RATING_REDUCE_NUM": null,
    "RATING_SALE_NUM": null,
    "SECURITY_CODE": "000425"
   },
   {
    "SECUCODE": "000425.SZ",
    "SECURITY_NAME_ABBR": "徐工机械",
    "SECURITY_INNER_CODE": "1000001764",
    "ORG_CODE": "10634817",
    "SECURITY_TYPE_CODE": "058001001",
    "TRADE_MARKET_CODE": "069001002001",
    "DATE_TYPE_CODE": 2,
    "DATE_TYPE": "2月内",
    "COMPRE_RATING_NUM": 4.75,
    "COMPRE_RATING": "买入",
    "RATING_ORG_NUM": 4,
    "RATING_BUY_NUM": 3,
    "RATING_ADD_NUM": 1,
    "RATING_NEUTRAL_NUM": null,
    "RATING_REDUCE_NUM": null,
    "RATING_SALE_NUM": null,
    "SECURITY_CODE": "000425"
   },
   {
    "SECUCODE": "000425.SZ",
    "SECURITY_NAME_ABBR": "徐工机械",
    "SECURITY_INNER_CODE": "1000001764",
    "ORG_CODE": "10634817",
    "SECURITY_TYPE_CODE": "058001001",
    "TRADE_MARKET_CODE": "069001002001",
    "DATE_TYPE_CODE": 3,
    "DATE_TYPE": "3月内",
    "COMPRE_RATING_NUM": 4.789473684211,
    "COMPRE_RATING": "买入",
    "RATING_ORG_NUM": 19,
    "RATING_BUY_NUM": 15,
    "RATING_ADD_NUM": 4,
    "RATING_NEUTRAL_NUM": null,
    "RATING_REDUCE_NUM": null,
    "RATING_SALE_NUM": null,
    "SECURITY_CODE": "000425"
   },
   {
    "SECUCODE": "000425.SZ",
    "SECURITY_NAME_ABBR": "徐工机械",
    "SECURITY_INNER_CODE": "1000001764",
    "ORG_CODE": "10634817",
    "SECURITY_TYPE_CODE": "058001001",
    "TRADE_MARKET_CODE": "069001002001",
    "DATE_TYPE_CODE": 4,
    "DATE_TYPE": "6月内",
    "COMPRE_RATING_NUM": 4.809523809524,
    "COMPRE_RATING": "买入",
    "RATING_ORG_NUM": 21,
    "RATING_BUY_NUM": 17,
    "RATING_ADD_NUM": 4,
    "RATING_NEUTRAL_NUM": null,
    "RATING_REDUCE_NUM": null,
    "RATING_SALE_NUM": null,
    "SECURITY_CODE": "000425"
   },
   {
    "SECUCODE": "000425.SZ",
    "SECURITY_NAME_ABBR": "徐工机械",
    "SECURITY_INNER_CODE": "1000001764",
    "ORG_CODE": "10634817",
    "SECURITY_TYPE_CODE": "058001001",
    "TRADE_MARKET_CODE": "069001002001",
    "DATE_TYPE_CODE": 5,
    "DATE_TYPE": "1年内",
    "COMPRE_RATING_NUM": 4.787878787879,
    "COMPRE_RATING": "买入",
    "RATING_ORG_NUM": 33,
    "RATING_BUY_NUM": 26,
    "RATING_ADD_NUM": 7,
    "RATING_NEUTRAL_NUM": null,
    "RATING_REDUCE_NUM": null,
    "RATING_SALE_NUM": null,
    "SECURITY_CODE": "000425"
   }
  ],
  "jgyc": [
   {
    "SECUCODE": "000425.SZ",
    "SECURITY_CODE": "000425",
    "SECURITY_NAME_ABBR": "徐工机械",
    "PUBLISH_DATE": "2026-07-10 00:00:00",
    "ORG_CODE": "00000000",
    "ORG_NAME_ABBR": "近六月平均",
    "YEAR1": 2025,
    "YEAR_MARK1": "A",
    "EPS1": 0.561190636347,
    "PE1": 15.02163339,
    "YEAR2": 2026,
    "YEAR_MARK2": "E",
    "EPS2": 0.712428571429,
    "PE2": 11.790071998198,
    "YEAR3": 2027,
    "YEAR_MARK3": "E",
    "EPS3": 0.895571428571,
    "PE3": 9.36164107576,
    "YEAR4": 2028,
    "YEAR_MARK4": "E",
    "EPS4": 1.079666666667,
    "PE4": 7.780111471812
   },
   {
    "SECUCODE": "000425.SZ",
    "SECURITY_CODE": "000425",
    "SECURITY_NAME_ABBR": "徐工机械",
    "PUBLISH_DATE": "2026-05-27 00:00:00",
    "ORG_CODE": "10004805",
    "ORG_NAME_ABBR": "华鑫证券",
    "YEAR1": 2025,
    "YEAR_MARK1": "A",
    "EPS1": 0.561190636347,
    "PE1": 15.02163339,
    "YEAR2": 2026,
    "YEAR_MARK2": "E",
    "EPS2": 0.66,
    "PE2": 12.727279113713,
    "YEAR3": 2027,
    "YEAR_MARK3": "E",
    "EPS3": 0.83,
    "PE3": 10.117391277421,
    "YEAR4": 2028,
    "YEAR_MARK4": "E",
    "EPS4": 0.97,
    "PE4": 8.666213490614
   },
   {
    "SECUCODE": "000425.SZ",
    "SECURITY_CODE": "000425",
    "SECURITY_NAME_ABBR": "徐工机械",
    "PUBLISH_DATE": "2026-05-26 00:00:00",
    "ORG_CODE": "10033793",
    "ORG_NAME_ABBR": "中邮证券",
    "YEAR1": 2025,
    "YEAR_MARK1": "A",
    "EPS1": 0.561190636347,
    "PE1": 15.02163339,
    "YEAR2": 2026,
    "YEAR_MARK2": "E",
    "EPS2": 0.67,
    "PE2": 12.607011120556,
    "YEAR3": 2027,
    "YEAR_MARK3": "E",
    "EPS3": 0.85,
    "PE3": 9.901264074323,
    "YEAR4": 2028,
    "YEAR_MARK4": "E",
    "EPS4": 1,
    "PE4": 8.468476933013
   },
   {
    "SECUCODE": "000425.SZ",
    "SECURITY_CODE": "000425",
    "SECURITY_NAME_ABBR": "徐工机械",
    "PUBLISH_DATE": "2026-05-15 00:00:00",
    "ORG_CODE": "10005685",
    "ORG_NAME_ABBR": "长江证券",
    "YEAR1": 2025,
    "YEAR_MARK1": "A",
    "EPS1": 0.561190636347,
    "PE1": 15.02163339,
    "YEAR2": 2026,
    "YEAR_MARK2": "E",
    "EPS2": 0.7,
    "PE2": 11.96962949625,
    "YEAR3": 2027,
    "YEAR_MARK3": "E",
    "EPS3": 0.9,
    "PE3": 9.287441588436,
    "YEAR4": 2028,
    "YEAR_MARK4": "E",
    "EPS4": 1.14,
    "PE4": 7.389633539302
   },
   {
    "SECUCODE": "000425.SZ",
    "SECURITY_CODE": "000425",
    "SECURITY_NAME_ABBR": "徐工机械",
    "PUBLISH_DATE": "2026-05-14 00:00:00",
    "ORG_CODE": "10055520",
    "ORG_NAME_ABBR": "麦高证券",
    "YEAR1": 2025,
    "YEAR_MARK1": "A",
    "EPS1": 0.561190636347,
    "PE1": 15.02163339,
    "YEAR2": 2026,
    "YEAR_MARK2": "E",
    "EPS2": 0.77,
    "PE2": 10.846572630748,
    "YEAR3": 2027,
    "YEAR_MARK3": "E",
    "EPS3": 0.9,
    "PE3": 9.349006068662,
    "YEAR4": 2028,
    "YEAR_MARK4": "E",
    "EPS4": 1.04,
    "PE4": 8.098228536221
   },
   {
    "SECUCODE": "000425.SZ",
    "SECURITY_CODE": "000425",
    "SECURITY_NAME_ABBR": "徐工机械",
    "PUBLISH_DATE": "2026-05-07 00:00:00",
    "ORG_CODE": "10053660",
    "ORG_NAME_ABBR": "财通证券",
    "YEAR1": 2025,
    "YEAR_MARK1": "A",
    "EPS1": 0.561190636347,
    "PE1": 15.02163339,
    "YEAR2": 2026,
    "YEAR_MARK2": "E",
    "EPS2": 0.72,
    "PE2": 11.689190952875,
    "YEAR3": 2027,
    "YEAR_MARK3": "E",
    "EPS3": 0.91,
    "PE3": 9.252884718883,
    "YEAR4": 2028,
    "YEAR_MARK4": "E",
    "EPS4": 1.13,
    "PE4": 7.4221387292
   },
   {
    "SECUCODE": "000425.SZ",
    "SECURITY_CODE": "000425",
    "SECURITY_NAME_ABBR": "徐工机械",
    "PUBLISH_DATE": "2026-05-07 00:00:00",
    "ORG_CODE": "10062057",
    "ORG_NAME_ABBR": "太平洋",
    "YEAR1": 2025,
    "YEAR_MARK1": "A",
    "EPS1": 0.561190636347,
    "PE1": 15.02163339,
    "YEAR2": 2026,
    "YEAR_MARK2": "E",
    "EPS2": 0.72,
    "PE2": 11.595666441751,
    "YEAR3": 2027,
    "YEAR_MARK3": "E",
    "EPS3": 0.91,
    "PE3": 9.203458943327,
    "YEAR4": 2028,
    "YEAR_MARK4": "E",
    "EPS4": 1.11,
    "PE4": 7.555908777366
   },
   {
    "SECUCODE": "000425.SZ",
    "SECURITY_CODE": "000425",
    "SECURITY_NAME_ABBR": "徐工机械",
    "PUBLISH_DATE": "2026-05-06 00:00:00",
    "ORG_CODE": "10004836",
    "ORG_NAME_ABBR": "东莞证券",
    "YEAR1": 2025,
    "YEAR_MARK1": "A",
    "EPS1": 0.561190636347,
    "PE1": 15.02163339,
    "YEAR2": 2026,
    "YEAR_MARK2": "E",
    "EPS2": 0.69,
    "PE2": 12.233643628881,
    "YEAR3": 2027,
    "YEAR_MARK3": "E",
    "EPS3": 0.85,
    "PE3": 9.828322955209,
    "YEAR4": 2028,
    "YEAR_MARK4": "E",
    "EPS4": 1.04,
    "PE4": 8.086289137937
   },
   {
    "SECUCODE": "000425.SZ",
    "SECURITY_CODE": "000425",
    "SECURITY_NAME_ABBR": "徐工机械",
    "PUBLISH_DATE": "2026-05-05 00:00:00",
    "ORG_CODE": "10002333",
    "ORG_NAME_ABBR": "国金证券",
    "YEAR1": 2025,
    "YEAR_MARK1": "A",
    "EPS1": 0.561190636347,
    "PE1": 15.02163339,
    "YEAR2": 2026,
    "YEAR_MARK2": "E",
    "EPS2": 0.681,
    "PE2": 12.342230789482,
    "YEAR3": 2027,
    "YEAR_MARK3": "E",
    "EPS3": 0.867,
    "PE3": 9.696081721182,
    "YEAR4": 2028,
    "YEAR_MARK4": "E",
    "EPS4": 1.094,
    "PE4": 7.678735637013
   },
   {
    "SECUCODE": "000425.SZ",
    "SECURITY_CODE": "000425",
    "SECURITY_NAME_ABBR": "徐工机械",
    "PUBLISH_DATE": "2026-05-05 00:00:00",
    "ORG_CODE": "10004927",
    "ORG_NAME_ABBR": "华创证券",
    "YEAR1": 2025,
    "YEAR_MARK1": "A",
    "EPS1": 0.561190636347,
    "PE1": 15.02163339,
    "YEAR2": 2026,
    "YEAR_MARK2": "E",
    "EPS2": 0.7,
    "PE2": 12.086863869377,
    "YEAR3": 2027,
    "YEAR_MARK3": "E",
    "EPS3": 0.86,
    "PE3": 9.744892319126,
    "YEAR4": 2028,
    "YEAR_MARK4": "E",
    "EPS4": 1.02,
    "PE4": 8.231927298013
   },
   {
    "SECUCODE": "000425.SZ",
    "SECURITY_CODE": "000425",
    "SECURITY_NAME_ABBR": "徐工机械",
    "PUBLISH_DATE": "2026-05-04 00:00:00",
    "ORG_CODE": "10004829",
    "ORG_NAME_ABBR": "光大证券",
    "YEAR1": 2025,
    "YEAR_MARK1": "A",
    "EPS1": 0.561190636347,
    "PE1": 15.02163339,
    "YEAR2": 2026,
    "YEAR_MARK2": "E",
    "EPS2": 0.75,
    "PE2": 11.217532562785,
    "YEAR3": 2027,
    "YEAR_MARK3": "E",
    "EPS3": 0.94,
    "PE3": 8.96526553624,
    "YEAR4": 2028,
    "YEAR_MARK4": "E",
    "EPS4": 1.11,
    "PE4": 7.546090658493
   },
   {
    "SECUCODE": "000425.SZ",
    "SECURITY_CODE": "000425",
    "SECURITY_NAME_ABBR": "徐工机械",
    "PUBLISH_DATE": "2026-05-04 00:00:00",
    "ORG_CODE": "10004876",
    "ORG_NAME_ABBR": "中国银河",
    "YEAR1": 2025,
    "YEAR_MARK1": "A",
    "EPS1": 0.561190636347,
    "PE1": 15.02163339,
    "YEAR2": 2026,
    "YEAR_MARK2": "E",
    "EPS2": 0.73,
    "PE2": 11.572559381675,
    "YEAR3": 2027,
    "YEAR_MARK3": "E",
    "EPS3": 0.95,
    "PE3": 8.799064535211,
    "YEAR4": 2028,
    "YEAR_MARK4": "E",
    "EPS4": 1.11,
    "PE4": 7.536873355605
   },
   {
    "SECUCODE": "000425.SZ",
    "SECURITY_CODE": "000425",
    "SECURITY_NAME_ABBR": "徐工机械",
    "PUBLISH_DATE": "2026-04-30 00:00:00",
    "ORG_CODE": "10004790",
    "ORG_NAME_ABBR": "东吴证券",
    "YEAR1": 2025,
    "YEAR_MARK1": "A",
    "EPS1": 0.561190636347,
    "PE1": 15.02163339,
    "YEAR2": 2026,
    "YEAR_MARK2": "E",
    "EPS2": 0.69,
    "PE2": 12.143358436048,
    "YEAR3": 2027,
    "YEAR_MARK3": "E",
    "EPS3": 0.87,
    "PE3": 9.635516697743,
    "YEAR4": 2028,
    "YEAR_MARK4": "E",
    "EPS4": 1.05,
    "PE4": 8.033648310283
   },
   {
    "SECUCODE": "000425.SZ",
    "SECURITY_CODE": "000425",
    "SECURITY_NAME_ABBR": "徐工机械",
    "PUBLISH_DATE": "2026-04-18 00:00:00",
    "ORG_CODE": "10004823",
    "ORG_NAME_ABBR": "方正证券",
    "YEAR1": 2025,
    "YEAR_MARK1": "A",
    "EPS1": 0.561190636347,
    "PE1": 15.02163339,
    "YEAR2": 2026,
    "YEAR_MARK2": "E",
    "EPS2": 0.78,
    "PE2": 10.755583841929,
    "YEAR3": 2027,
    "YEAR_MARK3": "E",
    "EPS3": 0.95,
    "PE3": 8.843201727434,
    "YEAR4": null,
    "YEAR_MARK4": null,
    "EPS4": null,
    "PE4": null
   },
   {
    "SECUCODE": "000425.SZ",
    "SECURITY_CODE": "000425",
    "SECURITY_NAME_ABBR": "徐工机械",
    "PUBLISH_DATE": "2026-03-25 00:00:00",
    "ORG_CODE": "10004830",
    "ORG_NAME_ABBR": "申万宏源",
    "YEAR1": 2025,
    "YEAR_MARK1": "A",
    "EPS1": 0.561190636347,
    "PE1": 15.02163339,
    "YEAR2": 2026,
    "YEAR_MARK2": "E",
    "EPS2": 0.73,
    "PE2": 11.557656764817,
    "YEAR3": 2027,
    "YEAR_MARK3": "E",
    "EPS3": 0.9,
    "PE3": 9.304948547132,
    "YEAR4": null,
    "YEAR_MARK4": null,
    "EPS4": null,
    "PE4": null
   }
  ],
  "yctj_chart": [
   {
    "SECUCODE": "000425.SZ",
    "SECURITY_CODE": "000425",
    "SECURITY_NAME_ABBR": "徐工机械",
    "YEAR": 2025,
    "YEAR_MARK": "A",
    "EPS": 0.561190636347,
    "EPS_RATIO": 8.9593534069,
    "PE": 15.02163339,
    "ROE": 11,
    "PARENT_NETPROFIT": 6572221644.27,
    "PARENT_NETPROFIT_RATIO": 8.959353407059,
    "TOTAL_OPERATE_INCOME": 100822903512.12,
    "TOTAL_OPERATE_INCOME_RATIO": 8.3681281147,
    "OPERATE_PROFIT": 7319362702.5,
    "RANK": 1
   },
   {
    "SECUCODE": "000425.SZ",
    "SECURITY_CODE": "000425",
    "SECURITY_NAME_ABBR": "徐工机械",
    "YEAR": 2026,
    "YEAR_MARK": "E",
    "EPS": 0.712428571429,
    "EPS_RATIO": 26.949475861899,
    "PE": 11.790071998198,
    "ROE": 12.539,
    "PARENT_NETPROFIT": 8373613333.33333,
    "PARENT_NETPROFIT_RATIO": 27.409174348736,
    "TOTAL_OPERATE_INCOME": 114962798571.429,
    "TOTAL_OPERATE_INCOME_RATIO": 14.024487062713,
    "OPERATE_PROFIT": 9172687894.73684,
    "RANK": 2
   },
   {
    "SECUCODE": "000425.SZ",
    "SECURITY_CODE": "000425",
    "SECURITY_NAME_ABBR": "徐工机械",
    "YEAR": 2027,
    "YEAR_MARK": "E",
    "EPS": 0.895571428571,
    "EPS_RATIO": 25.706837778223,
    "PE": 9.36164107576,
    "ROE": 14.178,
    "PARENT_NETPROFIT": 10545747619.0476,
    "PARENT_NETPROFIT_RATIO": 25.94022674856,
    "TOTAL_OPERATE_INCOME": 130631511904.762,
    "TOTAL_OPERATE_INCOME_RATIO": 13.62937709245,
    "OPERATE_PROFIT": 11544477894.7368,
    "RANK": 3
   },
   {
    "SECUCODE": "000425.SZ",
    "SECURITY_CODE": "000425",
    "SECURITY_NAME_ABBR": "徐工机械",
    "YEAR": 2028,
    "YEAR_MARK": "E",
    "EPS": 1.079666666667,
    "EPS_RATIO": 20.556175891955,
    "PE": 7.780111471812,
    "ROE": 15.459411764706,
    "PARENT_NETPROFIT": 12689471666.6667,
    "PARENT_NETPROFIT_RATIO": 20.327852752204,
    "TOTAL_OPERATE_INCOME": 146656156111.111,
    "TOTAL_OPERATE_INCOME_RATIO": 12.267058669605,
    "OPERATE_PROFIT": 13926129411.7647,
    "RANK": 4
   }
  ],
  "yctj_list": [
   {
    "SECUCODE": "000425.SZ",
    "SECURITY_CODE": "000425",
    "SECURITY_NAME_ABBR": "徐工机械",
    "YEAR": 2023,
    "YEAR_MARK": "A",
    "EPS": 0.454818083251,
    "EPS_LASTMONTHS": 0.454818083251,
    "BVPS": 4.751513302894,
    "ROE": 9.83,
    "PARENT_NETPROFIT": 5326470288.96,
    "TOTAL_OPERATE_INCOME": 92848220501.93,
    "OPERATE_PROFIT": 5640499062.7,
    "EPS_COUNT": null,
    "EPS_LASTMONTHS_COUNT": null,
    "BVPS_COUNT": null,
    "ROE_COUNT": null,
    "PARENT_NETPROFIT_COUNT": null,
    "TOTAL_OPERATE_INCOME_COUNT": null,
    "OPERATE_PROFIT_COUNT": null,
    "RANK": 1
   },
   {
    "SECUCODE": "000425.SZ",
    "SECURITY_CODE": "000425",
    "SECURITY_NAME_ABBR": "徐工机械",
    "YEAR": 2024,
    "YEAR_MARK": "A",
    "EPS": 0.515045857744,
    "EPS_LASTMONTHS": 0.515045857744,
    "BVPS": 5.037344913943,
    "ROE": 10.37,
    "PARENT_NETPROFIT": 6031810430.92,
    "TOTAL_OPERATE_INCOME": 93037413551.56,
    "OPERATE_PROFIT": 6625509098.45,
    "EPS_COUNT": null,
    "EPS_LASTMONTHS_COUNT": null,
    "BVPS_COUNT": null,
    "ROE_COUNT": null,
    "PARENT_NETPROFIT_COUNT": null,
    "TOTAL_OPERATE_INCOME_COUNT": null,
    "OPERATE_PROFIT_COUNT": null,
    "RANK": 2
   },
   {
    "SECUCODE": "000425.SZ",
    "SECURITY_CODE": "000425",
    "SECURITY_NAME_ABBR": "徐工机械",
    "YEAR": 2025,
    "YEAR_MARK": "A",
    "EPS": 0.561190636347,
    "EPS_LASTMONTHS": 0.561190636347,
    "BVPS": 5.144288933196,
    "ROE": 11,
    "PARENT_NETPROFIT": 6572221644.27,
    "TOTAL_OPERATE_INCOME": 100822903512.12,
    "OPERATE_PROFIT": 7319362702.5,
    "EPS_COUNT": null,
    "EPS_LASTMONTHS_COUNT": null,
    "BVPS_COUNT": null,
    "ROE_COUNT": null,
    "PARENT_NETPROFIT_COUNT": null,
    "TOTAL_OPERATE_INCOME_COUNT": null,
    "OPERATE_PROFIT_COUNT": null,
    "RANK": 3
   },
   {
    "SECUCODE": "000425.SZ",
    "SECURITY_CODE": "000425",
    "SECURITY_NAME_ABBR": "徐工机械",
    "YEAR": 2026,
    "YEAR_MARK": "E",
    "EPS": 0.712428571429,
    "EPS_LASTMONTHS": 0.712428571429,
    "BVPS": 5.321333333333,
    "ROE": 12.539,
    "PARENT_NETPROFIT": 8373613333.33333,
    "TOTAL_OPERATE_INCOME": 114962798571.429,
    "OPERATE_PROFIT": 9172687894.73684,
    "EPS_COUNT": 21,
    "EPS_LASTMONTHS_COUNT": 21,
    "BVPS_COUNT": 15,
    "ROE_COUNT": 20,
    "PARENT_NETPROFIT_COUNT": 21,
    "TOTAL_OPERATE_INCOME_COUNT": 21,
    "OPERATE_PROFIT_COUNT": 19,
    "RANK": 4
   },
   {
    "SECUCODE": "000425.SZ",
    "SECURITY_CODE": "000425",
    "SECURITY_NAME_ABBR": "徐工机械",
    "YEAR": 2027,
    "YEAR_MARK": "E",
    "EPS": 0.895571428571,
    "EPS_LASTMONTHS": 0.895571428571,
    "BVPS": 5.916,
    "ROE": 14.178,
    "PARENT_NETPROFIT": 10545747619.0476,
    "TOTAL_OPERATE_INCOME": 130631511904.762,
    "OPERATE_PROFIT": 11544477894.7368,
    "EPS_COUNT": 21,
    "EPS_LASTMONTHS_COUNT": 21,
    "BVPS_COUNT": 15,
    "ROE_COUNT": 20,
    "PARENT_NETPROFIT_COUNT": 21,
    "TOTAL_OPERATE_INCOME_COUNT": 21,
    "OPERATE_PROFIT_COUNT": 19,
    "RANK": 5
   },
   {
    "SECUCODE": "000425.SZ",
    "SECURITY_CODE": "000425",
    "SECURITY_NAME_ABBR": "徐工机械",
    "YEAR": 2028,
    "YEAR_MARK": "E",
    "EPS": 1.079666666667,
    "EPS_LASTMONTHS": 1.079666666667,
    "BVPS": 6.598357142857,
    "ROE": 15.459411764706,
    "PARENT_NETPROFIT": 12689471666.6667,
    "TOTAL_OPERATE_INCOME": 146656156111.111,
    "OPERATE_PROFIT": 13926129411.7647,
    "EPS_COUNT": 18,
    "EPS_LASTMONTHS_COUNT": 18,
    "BVPS_COUNT": 14,
    "ROE_COUNT": 17,
    "PARENT_NETPROFIT_COUNT": 18,
    "TOTAL_OPERATE_INCOME_COUNT": 18,
    "OPERATE_PROFIT_COUNT": 17,
    "RANK": 6
   }
  ],
  "ycmx": [
   {
    "SECUCODE": "000425.SZ",
    "SECURITY_CODE": "000425",
    "SECURITY_NAME_ABBR": "徐工机械",
    "SECURITY_INNER_CODE": "1000001764",
    "PUBLISH_DATE": "2026-05-27 00:00:00",
    "ORG_CODE": "10004805",
    "ORG_NAME_ABBR": "华鑫证券",
    "RESEARCHER": "尤少炜",
    "YEAR1": 2025,
    "YEAR_MARK1": "A",
    "EPS1": 0.561190636347,
    "PARENT_NETPROFIT1": 6572221644.27,
    "YEAR2": 2026,
    "YEAR_MARK2": "E",
    "EPS2": 0.66,
    "PARENT_NETPROFIT2": 7757000000,
    "YEAR3": 2027,
    "YEAR_MARK3": "E",
    "EPS3": 0.83,
    "PARENT_NETPROFIT3": 9758000000,
    "YEAR4": 2028,
    "YEAR_MARK4": "E",
    "EPS4": 0.97,
    "PARENT_NETPROFIT4": 11392000000,
    "RATING": "买入"
   },
   {
    "SECUCODE": "000425.SZ",
    "SECURITY_CODE": "000425",
    "SECURITY_NAME_ABBR": "徐工机械",
    "SECURITY_INNER_CODE": "1000001764",
    "PUBLISH_DATE": "2026-05-26 00:00:00",
    "ORG_CODE": "10033793",
    "ORG_NAME_ABBR": "中邮证券",
    "RESEARCHER": "刘卓,陈基赟",
    "YEAR1": 2025,
    "YEAR_MARK1": "A",
    "EPS1": 0.561190636347,
    "PARENT_NETPROFIT1": 6572221644.27,
    "YEAR2": 2026,
    "YEAR_MARK2": "E",
    "EPS2": 0.67,
    "PARENT_NETPROFIT2": 7831000000,
    "YEAR3": 2027,
    "YEAR_MARK3": "E",
    "EPS3": 0.85,
    "PARENT_NETPROFIT3": 9971000000,
    "YEAR4": 2028,
    "YEAR_MARK4": "E",
    "EPS4": 1,
    "PARENT_NETPROFIT4": 11658000000,
    "RATING": "买入"
   },
   {
    "SECUCODE": "000425.SZ",
    "SECURITY_CODE": "000425",
    "SECURITY_NAME_ABBR": "徐工机械",
    "SECURITY_INNER_CODE": "1000001764",
    "PUBLISH_DATE": "2026-05-15 00:00:00",
    "ORG_CODE": "10005685",
    "ORG_NAME_ABBR": "长江证券",
    "RESEARCHER": "赵智勇,臧雄,曹小敏",
    "YEAR1": 2025,
    "YEAR_MARK1": "A",
    "EPS1": 0.561190636347,
    "PARENT_NETPROFIT1": 6572221644.27,
    "YEAR2": 2026,
    "YEAR_MARK2": "E",
    "EPS2": 0.7,
    "PARENT_NETPROFIT2": 8248000000,
    "YEAR3": 2027,
    "YEAR_MARK3": "E",
    "EPS3": 0.9,
    "PARENT_NETPROFIT3": 10630000000,
    "YEAR4": 2028,
    "YEAR_MARK4": "E",
    "EPS4": 1.14,
    "PARENT_NETPROFIT4": 13360000000,
    "RATING": "买入"
   },
   {
    "SECUCODE": "000425.SZ",
    "SECURITY_CODE": "000425",
    "SECURITY_NAME_ABBR": "徐工机械",
    "SECURITY_INNER_CODE": "1000001764",
    "PUBLISH_DATE": "2026-05-14 00:00:00",
    "ORG_CODE": "10055520",
    "ORG_NAME_ABBR": "麦高证券",
    "RESEARCHER": "张骥,刘康衡",
    "YEAR1": 2025,
    "YEAR_MARK1": "A",
    "EPS1": 0.561190636347,
    "PARENT_NETPROFIT1": 6572221644.27,
    "YEAR2": 2026,
    "YEAR_MARK2": "E",
    "EPS2": 0.77,
    "PARENT_NETPROFIT2": 9102000000,
    "YEAR3": 2027,
    "YEAR_MARK3": "E",
    "EPS3": 0.9,
    "PARENT_NETPROFIT3": 10560000000,
    "YEAR4": 2028,
    "YEAR_MARK4": "E",
    "EPS4": 1.04,
    "PARENT_NETPROFIT4": 12191000000,
    "RATING": "买入"
   },
   {
    "SECUCODE": "000425.SZ",
    "SECURITY_CODE": "000425",
    "SECURITY_NAME_ABBR": "徐工机械",
    "SECURITY_INNER_CODE": "1000001764",
    "PUBLISH_DATE": "2026-05-07 00:00:00",
    "ORG_CODE": "10053660",
    "ORG_NAME_ABBR": "财通证券",
    "RESEARCHER": "佘炜超,郭亚新",
    "YEAR1": 2025,
    "YEAR_MARK1": "A",
    "EPS1": 0.561190636347,
    "PARENT_NETPROFIT1": 6572221644.27,
    "YEAR2": 2026,
    "YEAR_MARK2": "E",
    "EPS2": 0.72,
    "PARENT_NETPROFIT2": 8445880000,
    "YEAR3": 2027,
    "YEAR_MARK3": "E",
    "EPS3": 0.91,
    "PARENT_NETPROFIT3": 10669700000,
    "YEAR4": 2028,
    "YEAR_MARK4": "E",
    "EPS4": 1.13,
    "PARENT_NETPROFIT4": 13301490000,
    "RATING": "增持"
   },
   {
    "SECUCODE": "000425.SZ",
    "SECURITY_CODE": "000425",
    "SECURITY_NAME_ABBR": "徐工机械",
    "SECURITY_INNER_CODE": "1000001764",
    "PUBLISH_DATE": "2026-05-07 00:00:00",
    "ORG_CODE": "10062057",
    "ORG_NAME_ABBR": "太平洋",
    "RESEARCHER": "崔文娟,张凤琳",
    "YEAR1": 2025,
    "YEAR_MARK1": "A",
    "EPS1": 0.561190636347,
    "PARENT_NETPROFIT1": 6572221644.27,
    "YEAR2": 2026,
    "YEAR_MARK2": "E",
    "EPS2": 0.72,
    "PARENT_NETPROFIT2": 8514000000,
    "YEAR3": 2027,
    "YEAR_MARK3": "E",
    "EPS3": 0.91,
    "PARENT_NETPROFIT3": 10727000000,
    "YEAR4": 2028,
    "YEAR_MARK4": "E",
    "EPS4": 1.11,
    "PARENT_NETPROFIT4": 13066000000,
    "RATING": "买入"
   },
   {
    "SECUCODE": "000425.SZ",
    "SECURITY_CODE": "000425",
    "SECURITY_NAME_ABBR": "徐工机械",
    "SECURITY_INNER_CODE": "1000001764",
    "PUBLISH_DATE": "2026-05-06 00:00:00",
    "ORG_CODE": "10004836",
    "ORG_NAME_ABBR": "东莞证券",
    "RESEARCHER": "谢少威",
    "YEAR1": 2025,
    "YEAR_MARK1": "A",
    "EPS1": 0.561190636347,
    "PARENT_NETPROFIT1": 6572221644.27,
    "YEAR2": 2026,
    "YEAR_MARK2": "E",
    "EPS2": 0.69,
    "PARENT_NETPROFIT2": 8070000000,
    "YEAR3": 2027,
    "YEAR_MARK3": "E",
    "EPS3": 0.85,
    "PARENT_NETPROFIT3": 10045000000,
    "YEAR4": 2028,
    "YEAR_MARK4": "E",
    "EPS4": 1.04,
    "PARENT_NETPROFIT4": 12209000000,
    "RATING": "买入"
   },
   {
    "SECUCODE": "000425.SZ",
    "SECURITY_CODE": "000425",
    "SECURITY_NAME_ABBR": "徐工机械",
    "SECURITY_INNER_CODE": "1000001764",
    "PUBLISH_DATE": "2026-05-05 00:00:00",
    "ORG_CODE": "10002333",
    "ORG_NAME_ABBR": "国金证券",
    "RESEARCHER": "满在朋,倪赵义",
    "YEAR1": 2025,
    "YEAR_MARK1": "A",
    "EPS1": 0.561190636347,
    "PARENT_NETPROFIT1": 6572221644.27,
    "YEAR2": 2026,
    "YEAR_MARK2": "E",
    "EPS2": 0.681,
    "PARENT_NETPROFIT2": 7999000000,
    "YEAR3": 2027,
    "YEAR_MARK3": "E",
    "EPS3": 0.867,
    "PARENT_NETPROFIT3": 10182000000,
    "YEAR4": 2028,
    "YEAR_MARK4": "E",
    "EPS4": 1.094,
    "PARENT_NETPROFIT4": 12857000000,
    "RATING": "买入"
   },
   {
    "SECUCODE": "000425.SZ",
    "SECURITY_CODE": "000425",
    "SECURITY_NAME_ABBR": "徐工机械",
    "SECURITY_INNER_CODE": "1000001764",
    "PUBLISH_DATE": "2026-05-05 00:00:00",
    "ORG_CODE": "10004927",
    "ORG_NAME_ABBR": "华创证券",
    "RESEARCHER": "范益民,陈宏洋",
    "YEAR1": 2025,
    "YEAR_MARK1": "A",
    "EPS1": 0.561190636347,
    "PARENT_NETPROFIT1": 6572221644.27,
    "YEAR2": 2026,
    "YEAR_MARK2": "E",
    "EPS2": 0.7,
    "PARENT_NETPROFIT2": 8168000000,
    "YEAR3": 2027,
    "YEAR_MARK3": "E",
    "EPS3": 0.86,
    "PARENT_NETPROFIT3": 10131000000,
    "YEAR4": 2028,
    "YEAR_MARK4": "E",
    "EPS4": 1.02,
    "PARENT_NETPROFIT4": 11993000000,
    "RATING": "买入"
   },
   {
    "SECUCODE": "000425.SZ",
    "SECURITY_CODE": "000425",
    "SECURITY_NAME_ABBR": "徐工机械",
    "SECURITY_INNER_CODE": "1000001764",
    "PUBLISH_DATE": "2026-05-04 00:00:00",
    "ORG_CODE": "10004876",
    "ORG_NAME_ABBR": "中国银河",
    "RESEARCHER": "鲁佩",
    "YEAR1": 2025,
    "YEAR_MARK1": "A",
    "EPS1": 0.561190636347,
    "PARENT_NETPROFIT1": 6572221644.27,
    "YEAR2": 2026,
    "YEAR_MARK2": "E",
    "EPS2": 0.73,
    "PARENT_NETPROFIT2": 8531000000,
    "YEAR3": 2027,
    "YEAR_MARK3": "E",
    "EPS3": 0.95,
    "PARENT_NETPROFIT3": 11220000000,
    "YEAR4": 2028,
    "YEAR_MARK4": "E",
    "EPS4": 1.11,
    "PARENT_NETPROFIT4": 13099000000,
    "RATING": "买入"
   },
   {
    "SECUCODE": "000425.SZ",
    "SECURITY_CODE": "000425",
    "SECURITY_NAME_ABBR": "徐工机械",
    "SECURITY_INNER_CODE": "1000001764",
    "PUBLISH_DATE": "2026-05-04 00:00:00",
    "ORG_CODE": "10004829",
    "ORG_NAME_ABBR": "光大证券",
    "RESEARCHER": "陈佳宁,汲萌,夏天宇",
    "YEAR1": 2025,
    "YEAR_MARK1": "A",
    "EPS1": 0.561190636347,
    "PARENT_NETPROFIT1": 6572221644.27,
    "YEAR2": 2026,
    "YEAR_MARK2": "E",
    "EPS2": 0.75,
    "PARENT_NETPROFIT2": 8801000000,
    "YEAR3": 2027,
    "YEAR_MARK3": "E",
    "EPS3": 0.94,
    "PARENT_NETPROFIT3": 11012000000,
    "YEAR4": 2028,
    "YEAR_MARK4": "E",
    "EPS4": 1.11,
    "PARENT_NETPROFIT4": 13083000000,
    "RATING": "买入"
   },
   {
    "SECUCODE": "000425.SZ",
    "SECURITY_CODE": "000425",
    "SECURITY_NAME_ABBR": "徐工机械",
    "SECURITY_INNER_CODE": "1000001764",
    "PUBLISH_DATE": "2026-04-30 00:00:00",
    "ORG_CODE": "10004790",
    "ORG_NAME_ABBR": "东吴证券",
    "RESEARCHER": "周尔双,黄瑞",
    "YEAR1": 2025,
    "YEAR_MARK1": "A",
    "EPS1": 0.561190636347,
    "PARENT_NETPROFIT1": 6572221644.27,
    "YEAR2": 2026,
    "YEAR_MARK2": "E",
    "EPS2": 0.69,
    "PARENT_NETPROFIT2": 8130000000,
    "YEAR3": 2027,
    "YEAR_MARK3": "E",
    "EPS3": 0.87,
    "PARENT_NETPROFIT3": 10246000000,
    "YEAR4": 2028,
    "YEAR_MARK4": "E",
    "EPS4": 1.05,
    "PARENT_NETPROFIT4": 12289000000,
    "RATING": "买入"
   },
   {
    "SECUCODE": "000425.SZ",
    "SECURITY_CODE": "000425",
    "SECURITY_NAME_ABBR": "徐工机械",
    "SECURITY_INNER_CODE": "1000001764",
    "PUBLISH_DATE": "2026-04-18 00:00:00",
    "ORG_CODE": "10004823",
    "ORG_NAME_ABBR": "方正证券",
    "RESEARCHER": "赵璐,朱柏睿",
    "YEAR1": 2025,
    "YEAR_MARK1": "A",
    "EPS1": 0.561190636347,
    "PARENT_NETPROFIT1": 6572221644.27,
    "YEAR2": 2026,
    "YEAR_MARK2": "E",
    "EPS2": 0.78,
    "PARENT_NETPROFIT2": 9179000000,
    "YEAR3": 2027,
    "YEAR_MARK3": "E",
    "EPS3": 0.95,
    "PARENT_NETPROFIT3": 11164000000,
    "YEAR4": null,
    "YEAR_MARK4": null,
    "EPS4": null,
    "PARENT_NETPROFIT4": null,
    "RATING": "增持"
   },
   {
    "SECUCODE": "000425.SZ",
    "SECURITY_CODE": "000425",
    "SECURITY_NAME_ABBR": "徐工机械",
    "SECURITY_INNER_CODE": "1000001764",
    "PUBLISH_DATE": "2026-03-25 00:00:00",
    "ORG_CODE": "10004830",
    "ORG_NAME_ABBR": "申万宏源",
    "RESEARCHER": "王珂,李蕾,刘建伟,何佳霖",
    "YEAR1": 2025,
    "YEAR_MARK1": "A",
    "EPS1": 0.561190636347,
    "PARENT_NETPROFIT1": 6572221644.27,
    "YEAR2": 2026,
    "YEAR_MARK2": "E",
    "EPS2": 0.73,
    "PARENT_NETPROFIT2": 8542000000,
    "YEAR3": 2027,
    "YEAR_MARK3": "E",
    "EPS3": 0.9,
    "PARENT_NETPROFIT3": 10610000000,
    "YEAR4": null,
    "YEAR_MARK4": null,
    "EPS4": null,
    "PARENT_NETPROFIT4": null,
    "RATING": "买入"
   }
  ]
 }
}